gitmate.py
gitmatex-0.1.0.dist-info/METADATA
gitmatex-0.1.0.dist-info/WHEEL
gitmatex-0.1.0.dist-info/entry_points.txt
gitmatex-0.1.0.dist-info/top_level.txt
gitmatex-0.1.0.dist-info/RECORD
