Metadata-Version: 2.4
Name: gitmatex
Version: 0.1.0
Summary: A simple GitHub helper CLI tool
Author: Your Name
Author-email: youremail@gmail.com
Requires-Python: >=3.7
Requires-Dist: click
Dynamic: author
Dynamic: author-email
Dynamic: requires-dist
Dynamic: requires-python
Dynamic: summary
